schedulix/__init__.py
schedulix/scheduler.py
schedulix-0.0.2.dist-info/licenses/LICENSE
schedulix-0.0.2.dist-info/METADATA
schedulix-0.0.2.dist-info/WHEEL
schedulix-0.0.2.dist-info/top_level.txt
schedulix-0.0.2.dist-info/RECORD
