Metadata-Version: 2.4
Name: schedulix
Version: 0.0.2
Summary: A user friendly wrappr for scheduling tasks
Author-email: Nils Klasen <likeable.versed-78@icloud.com>
License-Expression: MIT
Project-URL: Homepage, https://git-ce.rwth-aachen.de/kls/schedulix
Project-URL: Documentation, https://schedulix-381cab.pages.git-ce.rwth-aachen.de
Project-URL: Issues, https://git-ce.rwth-aachen.de/kls/scheudlix/-/issues
Classifier: Programming Language :: Python :: 3.9
Classifier: Programming Language :: Python :: 3.10
Classifier: Programming Language :: Python :: 3.11
Classifier: Programming Language :: Python :: 3.12
Classifier: Operating System :: OS Independent
Requires-Python: <4,>=3.9
License-File: LICENSE
Dynamic: license-file
